[
  {
    "discipline": "3",
    "raceTo": "8",
    "status": "finished",
    "playerA": "Shoaib Momand",
    "playerB": "Otman Acharrat",
    "scoreA": "3",
    "scoreB": "8",
    "runoutsA": "",
    "runoutsB": "",
    "winner": 2
  },
  {
    "discipline": "2",
    "raceTo": "6",
    "status": "finished",
    "playerA": "Caro Line",
    "playerB": "Biao Wu",
    "scoreA": "6",
    "scoreB": "3",
    "runoutsA": "",
    "runoutsB": "",
    "winner": 1
  },
  {
    "discipline": "5",
    "raceTo": "75",
    "status": "finished",
    "playerA": "Shoaib Momand",
    "playerB": "Arno Brouwer",
    "scoreA": "66",
    "scoreB": "75",
    "runoutsA": "",
    "runoutsB": "",
    "winner": 2
  },
  {
    "discipline": "4",
    "raceTo": "6",
    "status": "finished",
    "playerA": "C.Line & R.Tsang",
    "playerB": "A.Brouwer & O.Acharrat",
    "scoreA": "2",
    "scoreB": "6",
    "runoutsA": "",
    "runoutsB": "",
    "winner": 2
  },
  {
    "discipline": "2",
    "raceTo": "6",
    "status": "finished",
    "playerA": "Richard Tsang",
    "playerB": "Arno Brouwer",
    "scoreA": "3",
    "scoreB": "6",
    "runoutsA": "",
    "runoutsB": "",
    "winner": 2
  },
  {
    "discipline": "3",
    "raceTo": "8",
    "status": "finished",
    "playerA": "Caro Line",
    "playerB": "Biao Wu",
    "scoreA": "8",
    "scoreB": "1",
    "runoutsA": "",
    "runoutsB": "",
    "winner": 1
  },
  {
    "discipline": "4",
    "raceTo": "7",
    "status": "finished",
    "playerA": "Richard Tsang",
    "playerB": "Otman Acharrat",
    "scoreA": "2",
    "scoreB": "7",
    "runoutsA": "",
    "runoutsB": "",
    "winner": 2
  }
]